clarityio/__init__.py
clarityio/clarityio.py
clarityio/scaling.py
clarityio-0.3.0.dist-info/METADATA
clarityio-0.3.0.dist-info/WHEEL
clarityio-0.3.0.dist-info/licenses/LICENSE
clarityio-0.3.0.dist-info/RECORD
