Metadata-Version: 2.3
Name: clarityio
Version: 0.3.0
Summary: Retrieve air quality data from the Clarity.io API
Project-URL: Homepage, https://github.com/a2gov/clarityio
Project-URL: Issues, https://github.com/a2gov/clarityio/issues
Author-email: Sam Firke <samuel.firke@gmail.com>
License-File: LICENSE
Classifier: License :: OSI Approved :: Apache Software License
Classifier: Operating System :: OS Independent
Classifier: Programming Language :: Python :: 3
Requires-Python: >=3.8
Requires-Dist: pytest>=6.0.0
Requires-Dist: requests>=2.0.0
